p_vs_np/__init__.py
p_vs_np/database_problems/3-satisfiability_(3sat).py
p_vs_np/database_problems/3_satisfiability_(3sat).py
p_vs_np/database_problems/Annihilation.py
p_vs_np/database_problems/Betweenness.py
p_vs_np/database_problems/Clustering.py
p_vs_np/database_problems/K-Relevancy.py
p_vs_np/database_problems/K_Relevancy.py
p_vs_np/database_problems/Knapsack.py
p_vs_np/database_problems/Non-Tautology.py
p_vs_np/database_problems/Non_Tautology.py
p_vs_np/database_problems/Satisfiability.py
p_vs_np/database_problems/Square-Tiling.py
p_vs_np/database_problems/Square_Tiling.py
p_vs_np/database_problems/__init__.py
p_vs_np/database_problems/additional_key.py
p_vs_np/database_problems/algebraic_equations_over_gf2.py
p_vs_np/database_problems/algebraic_equations_over_gf|2|.py
p_vs_np/database_problems/alternating__maximum_weighted_matching.py
p_vs_np/database_problems/alternating_hitting_set.py
p_vs_np/database_problems/boyce-codd_normal_form_violation.py
p_vs_np/database_problems/boyce_codd_normal_form_violation.py
p_vs_np/database_problems/chordal_graph_completion.py
p_vs_np/database_problems/chromatic_index.py
p_vs_np/database_problems/code_generation_for_parallel_assignments.py
p_vs_np/database_problems/code_generation_on_a_one-register_machine.py
p_vs_np/database_problems/code_generation_on_a_one_register_machine.py
p_vs_np/database_problems/code_generation_with_address_expressions.py
p_vs_np/database_problems/code_generation_with_unfixed_variable_locations.py
p_vs_np/database_problems/code_generation_with_unlimited_registers.py
p_vs_np/database_problems/comparative_divisibility.py
p_vs_np/database_problems/comparative_vector_inequalities.py
p_vs_np/database_problems/composite_number.py
p_vs_np/database_problems/conjunctive_boolean_query.py
p_vs_np/database_problems/conjunctive_query_foldability.py
p_vs_np/database_problems/conjunctive_satisfiability_with_functions_and_inequalities.py
p_vs_np/database_problems/consistency_of_database_frequency_tables.py
p_vs_np-1.0.0.dist-info/LICENSE
p_vs_np-1.0.0.dist-info/METADATA
p_vs_np-1.0.0.dist-info/WHEEL
p_vs_np-1.0.0.dist-info/entry_points.txt
p_vs_np-1.0.0.dist-info/top_level.txt
p_vs_np-1.0.0.dist-info/RECORD
