Metadata-Version: 2.1
Name: p-vs-np
Version: 1.0.0
Summary: A library for P vs NP problems.
Home-page: https://github.com/yourusername/p_vs_np
Author: Drew Simpson
Author-email: dsimps3@icloud.com
License: UNKNOWN
Platform: UNKNOWN
Classifier: Programming Language :: Python :: 3
Classifier: License :: OSI Approved :: MIT License
Classifier: Operating System :: OS Independent
Requires-Python: >=3.6
License-File: LICENSE
Requires-Dist: sympy
Requires-Dist: networkx
Requires-Dist: opencv-python
